License.txt
MANIFEST.in
README.md
RUNME.py
packaging.txt
requirements.txt
setup.py
maheshwariji/__init__.py
maheshwariji/ankit.py
maheshwariji.egg-info/PKG-INFO
maheshwariji.egg-info/SOURCES.txt
maheshwariji.egg-info/dependency_links.txt
maheshwariji.egg-info/top_level.txt