Metadata-Version: 1.0
Name: maheshwariji
Version: 0.0.1
Summary: Website : https://github.com/imvickykumar999/100th-Repository-Morsetor-python-Package
Home-page: https://imvickykumar999.herokuapp.com/news
Author: Ankit Malpani
Author-email: UNKNOWN
License: MIT
Keywords: class,python
Platform: UNKNOWN
